{
  "DOBONG": [
    "Banghak1(il)-dong",
    "Banghak2(i)-dong",
    "Banghak3(sam)-dong",
    "Chang1(il)-dong",
    "Chang2(i)-dong",
    "Chang3(sam)-dong",
    "Chang4(sa)-dong",
    "Chang5-dong",
    "Dobong1(il)-dong",
    "Dobong2(i)-dong",
    "Ssangmun1(il)-dong",
    "Ssangmun2(i)-dong",
    "Ssangmun3(sam)-dong",
    "Ssangmun4(sa)-dong"
  ],
  "DONGDAEMUN": [
    "Cheongnyangni-dong",
    "Dapsip-ri1(il)-dong",
    "Dapsip-ri2(i)-dong",
    "Hoegi-dong",
    "Hwigyeong1(il)-dong",
    "Hwigyeong2(i)-dong",
    "Imun2(i)-dong",
    "Jangan1(il)-dong",
    "Jangan2(i)-dong",
    "Jeonnong1(il)-dong",
    "Jeonnong2(i)-dong",
    "Yongshin-dong"
  ],
  "DONGJAK": [
    "Daebang-dong",
    "Heukseok-dong",
    "Noryangjin1(il)-dong",
    "Noryangjin2(i)-dong",
    "Sadang1(il)-dong",
    "Sadang2(i)-dong",
    "Sadang3(sam)-dong",
    "Sadang4(sa)-dong",
    "Sadang5(o)-dong",
    "Sang-do1(il)-dong",
    "Sang-do3(sam)-dong",
    "Sang-do4(sa)-dong",
    "Sindaebang1(il)-dong",
    "Sindaebang2(i)-dong"
  ],
  "EUNPYEONG": [
    "Bulgwang1(il)-dong",
    "Bulgwang2(i)-dong",
    "Daejo-dong",
    "Eungam1(il)-dong",
    "Eungam2(i)-dong",
    "Eungam3(sam)-dong",
    "Galhyeon1(il)-dong",
    "Galhyeon2(i)-dong",
    "Gusan-dong",
    "Jeungsan-dong",
    "Jingwan-dong",
    "Nokbeon-dong",
    "Sinsa1(il)-dong",
    "Susaek-dong"
  ],
  "GANGBUK": [
    "Beon1(il)-dong",
    "Beon2(i)-dong",
    "Beon3(sam)-dong",
    "Insu-dong",
    "Mia-dong",
    "Samgaksan-dong",
    "Samyang-dong",
    "Songcheon-dong",
    "Suyu1(il)-dong",
    "Suyu2(i)-dong",
    "Suyu3(sam)-dong",
    "Ui-dong"
  ],
  "GANGDONG": [
    "Amsa1(il)-dong",
    "Amsa2(i)-dong",
    "Amsa3(sam)-dong",
    "Cheonho1(il)-dong",
    "Cheonho2(i)-dong",
    "Cheonho3(sam)-dong",
    "Deungchon1(il)-dong",
    "Dunchon1(il)-dong",
    "Dunchon2(i)-dong",
    "Gangil-dong",
    "Gil-dong",
    "Godeok1(il)-dong",
    "Godeok2(i)-dong",
    "Myeon-gil1(il)-dong",
    "Myeon-gil2(i)-dong",
    "Sangil-dong",
    "Seongnae1(il)-dong",
    "Seongnae2(i)-dong",
    "Seongnae3(sam)-dong"
  ],
  "GANGNAM": [
    "Apgujeong-dong",
    "Cheongdam-dong",
    "Daechi1(il)-dong",
    "Daechi2(i)-dong",
    "Daechi4(sa)-dong",
    "Dogok1(il)-dong",
    "Dogok2(i)-dong",
    "Gaepo1(il)-dong",
    "Gaepo2(i)-dong",
    "Gaepo4(sa)-dong",
    "Ilwon1(il)-dong",
    "Ilwon2(i)-dong",
    "Ilwonbon-dong",
    "Nonhyeon1(il)-dong",
    "Nonhyeon2(i)-dong",
    "Samseong1(il)-dong",
    "Samseong2(i)-dong",
    "Segok-dong",
    "Sinsa-dong",
    "Suseo-dong",
    "Yeoksam1(il)-dong",
    "Yeoksam2(i)-dong"
  ],
  "GANGSEO": [
    "Balsan1(il)-dong",
    "Banghwa1(il)-dong",
    "Banghwa2(i)-dong",
    "Banghwa3(sam)-dong",
    "Deungchon1(il)-dong",
    "Deungchon2(i)-dong",
    "Gayang1(il)-dong",
    "Gayang2(i)-dong",
    "Gayang3(sam)-dong",
    "Gonghang-dong",
    "Hwagok1(il)-dong",
    "Hwagok2(i)-dong",
    "Hwagok3(sam)-dong",
    "Hwagok4(sa)-dong",
    "Hwagok6(yuk)-dong",
    "Hwagok8(pal)-dong",
    "Hwagokbon-dong",
    "Ujangsan-dong",
    "Yeomchang-dong"
  ],
  "GEUMCHEON": [
    "Doksan1(il)-dong",
    "Doksan2(i)-dong",
    "Doksan4(sa)-dong",
    "Gasan-dong",
    "Siheung1(il)-dong",
    "Siheung2(i)-dong",
    "Siheung3(sam)-dong",
    "Siheung4(sa)-dong",
    "Siheung5(o)-dong"
  ],
  "GURO": [
    "Gaebong1(il)-dong",
    "Gaebong2(i)-dong",
    "Gaebong3(sam)-dong",
    "Garibong-dong",
    "Gocheok1(il)-dong",
    "Gocheok2(i)-dong",
    "Gu-ro1(il)-dong",
    "Gu-ro2(i)-dong",
    "Gu-ro3(sam)-dong",
    "Gu-ro4(sa)-dong",
    "Gu-ro5(o)-dong",
    "Hang-dong",
    "Oryu1(il)-dong",
    "Oryu2(i)-dong",
    "Sindorim-dong",
    "Sugung-dong"
  ],
  "GWANAK": [
    "Boramae-dong",
    "Cheongnim-dong",
    "Cheongnyong-dong",
    "Daehak-dong",
    "Euncheon-dong",
    "Haengun-dong",
    "Inheon-dong",
    "Jowon-dong",
    "Jungang-dong",
    "Miseong-dong",
    "Nakseongdae-dong",
    "Namhyeon-dong",
    "Nangok-dong",
    "Nanhyang-dong",
    "Samseong-dong",
    "Seonghyeon-dong",
    "Seorim-dong",
    "Seowon-dong",
    "Sinllim-dong",
    "Sinsa-dong",
    "Sinwon-dong",
    "Sungin1(il)-dong",
    "Yeomchang-dong"
  ],
  "GWANGJIN": [
    "Gunja-dong",
    "Guui1(il)-dong",
    "Guui2(i)-dong",
    "Guui3(sam)-dong",
    "Gwangjang-dong",
    "Hwayang-dong",
    "Jayang1(il)-dong",
    "Jayang2(i)-dong",
    "Jayang3(sam)-dong",
    "Jayang4(sa)-dong",
    "Junggok1(il)-dong",
    "Junggok2(i)-dong",
    "Junggok3(sam)-dong",
    "Junggok4(sa)-dong",
    "Neung-dong"
  ],
  "JONGNO": [
    "Buam-dong",
    "Changsin1(il)-dong",
    "Changsin2(i)-dong",
    "CheongwoonHyoja-dong",
    "Dongseon-dong",
    "Gahoe-dong",
    "Gyonam-dong",
    "Hyehwa-dong",
    "Ihwa-dong",
    "Jeonnong3(sam)-dong",
    "Jong-ro1(il).2(i).3(sam",
    "Jong-ro5(o).6(yuk)-ga-d",
    "Muak-dong",
    "Pyeongchang-dong",
    "Sajik-dong",
    "Samcheong-dong",
    "Sungin2(i)-dong"
  ],
  "JUNG": [
    "Changsin1(il)-dong",
    "Dasan-dong",
    "Donghwa-dong",
    "Eulji-ro-dong",
    "Gwanghui-dong",
    "Hoehyeon-dong",
    "Hwanghak-dong",
    "Jangchung-dong",
    "Jeonnong3(sam)-dong",
    "Jong-ro1(il).2(i).3(sam",
    "Jungnim-dong",
    "Myeong-dong",
    "Pil-dong",
    "Sindang5(o)-dong",
    "Sindang-dong",
    "Sogong-dong",
    "Yaksu-dong"
  ],
  "JUNGNANG": [
    "Junghwa1(il)-dong",
    "Junghwa2(i)-dong",
    "Man-gu3(sam)-dong",
    "Mangubon-dong",
    "Muk1(il)-dong",
    "Muk2(i)-dong",
    "Myeonmok3(sam).8(pal)-d",
    "Myeonmok4(sa)-dong",
    "Myeonmok5(o)-dong",
    "Myeonmokbon-dong",
    "Sangbong1(il)-dong",
    "Sangbong2(i)-dong",
    "Sinnae1(il)-dong",
    "Sinnae2(i)-dong"
  ],
  "MAPO": [
    "Ahyeon-dong",
    "Daeheung-dong",
    "Dohwa-dong",
    "Gongdeok-dong",
    "Hapjeong-dong",
    "Mangwon1(il)-dong",
    "Mangwon2(i)-dong",
    "Sangam-dong",
    "Seogyo-dong",
    "Seongsan1(il)-dong",
    "Seongsan2(i)-dong",
    "Sinsu-dong",
    "Sogang-dong",
    "Yeomni-dong",
    "Yeonnam-dong",
    "Yonggang-dong"
  ],
  "NOWON": [
    "Gongneung1(il)-dong",
    "Gongneung2(i)-dong",
    "Hagye1(il)-dong",
    "Hagye2(i)-dong",
    "Junggye1(il)-dong",
    "Junggye4(sa)-dong",
    "Junggyebon-dong",
    "Sanggye1(il)-dong",
    "Sanggye10(sip)-dong",
    "Sanggye2(i)-dong",
    "Sanggye3(sam).4(sa)-don",
    "Sanggye5(o)-dong",
    "Sanggye6(yuk).7(chil)-d",
    "Sanggye8(pal)-dong",
    "Sanggye9(gu)-dong",
    "Wolgye1(il)-dong",
    "Wolgye2(i)-dong",
    "Wolgye3(sam)-dong"
  ],
  "SEOCHO": [
    "Bangbae1(il)-dong",
    "Bangbae2(i)-dong",
    "Bangbae3(sam)-dong",
    "Bangbae4(sa)-dong",
    "Banpo1(il)-dong",
    "Banpo2(i)-dong",
    "Banpo3(sam)-dong",
    "Banpo4(sa)-dong",
    "Banpobon-dong",
    "Jamwon-dong",
    "Naegok-dong",
    "Seocho1(il)-dong",
    "Seocho2(i)-dong",
    "Seocho3(sam)-dong",
    "Seocho4(sa)-dong",
    "Yangjae1(il)-dong",
    "Yangjae2(i)-dong"
  ],
  "SEODAEMUN": [
    "Bukahyeon-dong",
    "Bukgajwa1(il)-dong",
    "Bukgajwa2(i)-dong",
    "Cheonyeon-dong",
    "Chunghyeon-dong",
    "Hongeun1(il)-dong",
    "Hongeun2(i)-dong",
    "Hongje1(il)-dong",
    "Hongje3(sam)-dong",
    "Namgajwa1(il)-dong",
    "Namgajwa2(i)-dong",
    "Sinchon-dong",
    "Yeonhui-dong"
  ],
  "SEONGBUK": [
    "Anam-dong",
    "Bomun-dong",
    "Donam1(il)-dong",
    "Donam2(i)-dong",
    "Dongseon-dong",
    "Gileum1(il)-dong",
    "Gileum2(i)-dong",
    "Jangwi1(il)-dong",
    "Jangwi2(i)-dong",
    "Jangwi3(sam)-dong",
    "Jeongneung1(il)-dong",
    "Jeongneung2(i)-dong",
    "Jeongneung3(sam)-dong",
    "Jeongneung4(sa)-dong",
    "Jongam-dong",
    "Samseon-dong",
    "Seokgwan-dong",
    "Seongbuk-dong",
    "Wolgok1(il)-dong",
    "Wolgok2(i)-dong"
  ],
  "SEONGDONG": [
    "Eungbong-dong",
    "Geumho-1(il)-dong",
    "Geumho-2.3(i)(sam)-dong",
    "Geumho4(sa)-dong",
    "Haengdang1(il)-dong",
    "Haengdang2(i)-dong",
    "Majang-dong",
    "Oksu-dong",
    "Sageun-dong",
    "Seongsu1ga1(il)-dong",
    "Seongsu1ga2(i)-dong",
    "Seongsu2ga1(il)-dong",
    "Seongsu2ga3(sam)-dong",
    "Songjeong-dong",
    "Wangsimni2(i)-dong",
    "Wangsimni-doSeondong",
    "Yongdap-dong"
  ],
  "SONGPA": [
    "Bangi1(il)-dong",
    "Bangi2(i)-dong",
    "Garak2(i)-dong",
    "Garakbon-dong",
    "Geoyeo1(il)-dong",
    "Geoyeo2(i)-dong",
    "Jamsil2(i)-dong",
    "Jamsil3(sam)-dong",
    "Jamsil4(sa)-dong",
    "Jamsil6(yuk)-dong",
    "Jamsil7(chil)-dong",
    "Jamsilbon-dong",
    "Jangji-dong",
    "Macheon2(i)-dong",
    "Munjeong1(il)-dong",
    "Munjeong2(i)-dong",
    "Ogeum-dong",
    "Oryun-dong",
    "Pungnap1(il)-dong",
    "Pungnap2(i)-dong",
    "Samjeon-dong",
    "Seokchon-dong",
    "Songpa1(il)-dong",
    "Songpa2(i)-dong",
    "Wirye-dong"
  ],
  "YANGCHEON": [
    "Dangsan2(i)-dong",
    "Mok1(il)-dong",
    "Mok2(i)-dong",
    "Mok3(sam)-dong",
    "Mok4(sa)-dong",
    "Mok5(o)-dong",
    "Sinjeong1(il)-dong",
    "Sinjeong2(i)-dong",
    "Sinjeong3(sam)-dong",
    "Sinjeong4(sa)-dong",
    "Sinjeong6(yuk)-dong",
    "Sinjeong7(chil)-dong",
    "Sinwol1(il)-dong",
    "Sinwol2(i)-dong",
    "Sinwol3(sam)-dong",
    "Sinwol4(sa)-dong",
    "Sinwol5(o)-dong",
    "Sinwol6(yuk)-dong",
    "Sinwol7(chil)-dong"
  ],
  "YEONGDEUNGPO": [
    "Daerim2(i)-dong",
    "Daerim3(sam)-dong",
    "Dangsan1(il)-dong",
    "Dangsan2(i)-dong",
    "Dorim-dong",
    "Munllae-dong",
    "Sin-gil1(il)-dong",
    "Sin-gil4(sa)-dong",
    "Sin-gil5(o)-dong",
    "Sin-gil6(yuk)-dong",
    "Sin-gil7(chil)-dong",
    "Yangpyeong1(il)-dong",
    "Yangpyeong2(i)-dong",
    "Yeongdeungpo-dong",
    "Yeouido-dong"
  ],
  "YONGSAN": [
    "Bogwang-dong",
    "Hangang-ro-dong",
    "Hannam-dong",
    "Huam-dong",
    "Hyochang-dong",
    "Ichon1(il)-dong",
    "Ichon2(i)-dong",
    "Itaewon1(il)-dong",
    "Itaewon2(i)-dong",
    "Seobinggo-dong",
    "Wonhyo-ro-1(il)-dong",
    "Wonhyo-ro-2(i)-dong",
    "Yongmun-dong",
    "Yongsan2(i)-dong"
  ]
}
